{"HeWeather5":[{"basic":{"city":"昆明","cnty":"中国","id":"CN101290101","lat":"25.04060936","lon":"102.71224976","update":{"loc":"2017-07-25 17:49","utc":"2017-07-25 09:49"}},"daily_forecast":[{"astro":{"mr":"08:17","ms":"21:33","sr":"06:34","ss":"19:59"},"cond":{"code_d":"305","code_n":"300","txt_d":"小雨","txt_n":"阵雨"},"date":"2017-07-25","hum":"70","pcpn":"12.1","pop":"100","pres":"1006","tmp":{"max":"25","min":"17"},"uv":"13","vis":"14","wind":{"deg":"0","dir":"无持续风向","sc":"微风","spd":"4"}},{"astro":{"mr":"09:19","ms":"22:16","sr":"06:35","ss":"19:58"},"cond":{"code_d":"300","code_n":"101","txt_d":"阵雨","txt_n":"多云"},"date":"2017-07-26","hum":"67","pcpn":"1.0","pop":"17","pres":"1006","tmp":{"max":"26","min":"17"},"uv":"13","vis":"19","wind":{"deg":"0","dir":"无持续风向","sc":"微风","spd":"3"}},{"astro":{"mr":"10:17","ms":"22:56","sr":"06:35","ss":"19:58"},"cond":{"code_d":"101","code_n":"101","txt_d":"多云","txt_n":"多云"},"date":"2017-07-27","hum":"64","pcpn":"0.1","pop":"82","pres":"1006","tmp":{"max":"27","min":"18"},"uv":"13","vis":"19","wind":{"deg":"0","dir":"无持续风向","sc":"微风","spd":"4"}}],"status":"ok"}]}